fairylandfuture/__init__.py
fairylandfuture/api/__init__.py
fairylandfuture/common/__init__.py
fairylandfuture/conf/__init__.py
fairylandfuture/conf/requirements.in
fairylandfuture/conf/release/commit-version
fairylandfuture/conf/release/logo
fairylandfuture/constants/__init__.py
fairylandfuture/constants/enums.py
fairylandfuture/constants/typed.py
fairylandfuture/core/__init__.py
fairylandfuture/core/abstracts/__init__.py
fairylandfuture/core/abstracts/databases.py
fairylandfuture/core/abstracts/metaclass.py
fairylandfuture/core/metaclasses/__init__.py
fairylandfuture/core/metaclasses/model.py
fairylandfuture/core/metaclasses/singleton.py
fairylandfuture/core/superclass/__init__.py
fairylandfuture/core/superclass/decorators.py
fairylandfuture/core/superclass/enumerate.py
fairylandfuture/core/superclass/files.py
fairylandfuture/core/superclass/metaclass.py
fairylandfuture/core/superclass/structures.py
fairylandfuture/core/superclass/object/__init__.py
fairylandfuture/core/superclass/object/property.py
fairylandfuture/helpers/__init__.py
fairylandfuture/models/__init__.py
fairylandfuture/models/orm/__init__.py
fairylandfuture/models/orm/general.py
fairylandfuture/models/orm/fields/__init__.py
fairylandfuture/models/orm/fields/descriptor.py
fairylandfuture/modules/__init__.py
fairylandfuture/modules/datetimes.py
fairylandfuture/modules/decorators.py
fairylandfuture/modules/exceptions.py
fairylandfuture/modules/journal.py
fairylandfuture/modules/cryptos/__init__.py
fairylandfuture/modules/cryptos/cipher.py
fairylandfuture/modules/cryptos/encoder.py
fairylandfuture/modules/databases/__init__.py
fairylandfuture/modules/databases/mysql.py
fairylandfuture/modules/databases/postgresql.py
fairylandfuture/modules/django/__init__.py
fairylandfuture/modules/django/settings.py
fairylandfuture/modules/files/__init__.py
fairylandfuture/modules/files/general.py
fairylandfuture/modules/networking/__init__.py
fairylandfuture/modules/networking/local.py
PyFairylandFuture-1.1.0.dist-info/LICENSE.txt
PyFairylandFuture-1.1.0.dist-info/METADATA
PyFairylandFuture-1.1.0.dist-info/WHEEL
PyFairylandFuture-1.1.0.dist-info/top_level.txt
PyFairylandFuture-1.1.0.dist-info/RECORD
