Metadata-Version: 2.1
Name: PyFairylandFuture
Version: 1.1.0
Summary: Efficient developed Python library.
Home-page: https://github.com/PrettiestFairy/pypi-fairylandfuture
Author: Lionel Johnson
Author-email: fairylandfuture@outlook.com
Keywords: fairyland,Fairyland,pyfairyland,PyFairyland,fairy,Fairy,fairylandfuture,PyFairylandFuture,FairylandFuture
Classifier: Programming Language :: Python :: 3
Classifier: Programming Language :: Python :: 3.8
Classifier: Programming Language :: Python :: 3.9
Classifier: Programming Language :: Python :: 3.10
Classifier: Programming Language :: Python :: 3.11
Classifier: Programming Language :: Python :: 3.12
Classifier: Programming Language :: Python :: Implementation :: CPython
Classifier: Programming Language :: Python :: Implementation :: PyPy
Classifier: Programming Language :: SQL
Classifier: Framework :: Django :: 4
Classifier: Framework :: Flask
Classifier: Framework :: FastAPI
Classifier: Framework :: Flake8
Classifier: Framework :: IPython
Classifier: Framework :: Jupyter
Classifier: Framework :: Scrapy
Classifier: Natural Language :: English
Classifier: Natural Language :: Chinese (Simplified)
Classifier: Operating System :: Microsoft :: Windows :: Windows 10
Classifier: Operating System :: Microsoft :: Windows :: Windows 11
Classifier: Operating System :: POSIX :: Linux
Classifier: Topic :: Software Development :: Libraries :: Python Modules
Classifier: Topic :: Software Development :: Libraries :: Application Frameworks
Classifier: Topic :: Software Development :: Version Control :: Git
Classifier: Topic :: System :: Operating System Kernels :: Linux
Classifier: License :: OSI Approved :: GNU Affero General Public License v3 or later (AGPLv3+)
Requires-Python: >=3.8
License-File: LICENSE.txt
Requires-Dist: pip-tools
Requires-Dist: pipreqs
Requires-Dist: flake8
Requires-Dist: isort
Requires-Dist: black
Requires-Dist: mypy
Requires-Dist: pydocstyle
Requires-Dist: pylint
Requires-Dist: autopep8
Requires-Dist: pylama
Requires-Dist: pigar
Requires-Dist: pipdeptree
Requires-Dist: pip-review
Requires-Dist: pip-autoremove
Requires-Dist: setuptools
Requires-Dist: loguru
Requires-Dist: python-dateutil
Requires-Dist: requests
Requires-Dist: pymysql
Requires-Dist: pyyaml
Requires-Dist: netifaces
Requires-Dist: cryptography
Requires-Dist: python-dotenv
Requires-Dist: psycopg2
Requires-Dist: psycopg2-binary
Requires-Dist: django
Requires-Dist: djangorestframework
Requires-Dist: markdown
Requires-Dist: django-filter
